perceptron/__init__.py
perceptron/perceptron_class.py
Perceptron12_pypi_noob_coder_dev-0.0.4.dist-info/LICENSE
Perceptron12_pypi_noob_coder_dev-0.0.4.dist-info/METADATA
Perceptron12_pypi_noob_coder_dev-0.0.4.dist-info/WHEEL
Perceptron12_pypi_noob_coder_dev-0.0.4.dist-info/top_level.txt
Perceptron12_pypi_noob_coder_dev-0.0.4.dist-info/RECORD
