Metadata-Version: 2.1
Name: Perceptron12-pypi-noob-coder-dev
Version: 0.0.4
Summary: It's a real-life implementation of McCulloch-Pitts Neuron Model
Home-page: https://github.com/noob-coder-dev/Perceptron12_pypi
Author: Manojit Roy
Author-email: roy.monojit982810@gmail.com
License: UNKNOWN
Project-URL: Bug Tracker, https://github.com/noob-coder-dev/Perceptron12_pypi/issues
Platform: UNKNOWN
Classifier: Programming Language :: Python :: 3
Classifier: License :: OSI Approved :: MIT License
Classifier: Operating System :: OS Independent
Requires-Python: >=3.8
License-File: LICENSE
Requires-Dist: numpy
Requires-Dist: tqdm
